{
    "key": "group_6089a4508b72f",
    "title": "28 - Formation",
    "fields": [],
    "location": [
        [
            {
                "param": "block",
                "operator": "==",
                "value": "acf\/module-28-formation"
            }
        ]
    ],
    "menu_order": 0,
    "position": "normal",
    "style": "default",
    "label_placement": "top",
    "instruction_placement": "label",
    "hide_on_screen": "",
    "active": true,
    "description": "",
    "modified": 1619633324
}